magv/__init__.py
magv/__main__.py
magv/default.py
magv/gitrepo.py
magv/install.py
magv/integrity.py
magv/pgxn.py
magv-0.2.2.dist-info/LICENSE
magv-0.2.2.dist-info/METADATA
magv-0.2.2.dist-info/WHEEL
magv-0.2.2.dist-info/top_level.txt
magv-0.2.2.dist-info/RECORD
